weavery/__init__.py
weavery/utils.py
weavery-0.0.3.dist-info/DESCRIPTION.rst
weavery-0.0.3.dist-info/METADATA
weavery-0.0.3.dist-info/RECORD
weavery-0.0.3.dist-info/WHEEL
weavery-0.0.3.dist-info/metadata.json
weavery-0.0.3.dist-info/top_level.txt
